clipboard_text_correction/__init__.py
clipboard_text_correction/about.py
clipboard_text_correction/desktop.py
clipboard_text_correction/indicator.py
clipboard_text_correction/lib_files.py
clipboard_text_correction/lib_funcs.py
clipboard_text_correction/lib_latex.py
clipboard_text_correction/lib_md2html.py
clipboard_text_correction/lib_stats.py
clipboard_text_correction/lib_textdiff.py
clipboard_text_correction/data/article_format.json
clipboard_text_correction/icons/logo.png
clipboard_text_correction-0.2.19.dist-info/licenses/LICENSE
clipboard_text_correction-0.2.19.dist-info/METADATA
clipboard_text_correction-0.2.19.dist-info/WHEEL
clipboard_text_correction-0.2.19.dist-info/entry_points.txt
clipboard_text_correction-0.2.19.dist-info/top_level.txt
clipboard_text_correction-0.2.19.dist-info/RECORD
