Metadata-Version: 2.4
Name: clipboard_text_correction
Version: 0.2.19
Summary: Program that collects text from the clipboard and improves text writing
Author-email: Fernando Pujaico Rivera <fernando.pujaico.rivera@gmail.com>
Maintainer-email: Fernando Pujaico Rivera <fernando.pujaico.rivera@gmail.com>
License-Expression: GPL-3.0-only WITH Classpath-exception-2.0 OR BSD-3-Clause
Project-URL: Bug Reports, https://github.com/trucomanx/ClipboardTextCorrection/issues
Project-URL: Funding, https://trucomanx.github.io/en/funding.html
Project-URL: Source, https://github.com/trucomanx/ClipboardTextCorrection
Keywords: writing,spelling
Classifier: Programming Language :: Python :: 3
Classifier: Operating System :: OS Independent
Requires-Python: >=3.8
License-File: LICENSE
Requires-Dist: PyQt5
Requires-Dist: deep-consultation
Requires-Dist: textstat
Requires-Dist: markdown
Dynamic: license-file
